{
	"name": "base_ghost_details",
	"dependencies": [
		["after", "name", "base_monomap"]
	],
	"data": [
		["base:ghost_details_map", {
			"base:item/wooden_wall": ["base:ghost/wooden_wall", "base:tileset/monomap", true,  32,  6, 0, 2],
			"base:item/plant_pot1":  ["base:ghost/normal",      "base:tileset/monomap", false, 32, 12, 4, 2],
			"base:item/plant_pot2":  ["base:ghost/normal",      "base:tileset/monomap", false, 32, 12, 5, 2],
			"base:item/plant_pot3":  ["base:ghost/normal",      "base:tileset/monomap", false, 32, 12, 6, 2],
			"base:item/tower":       ["base:ghost/tower",       "base:tileset/monomap", true,  32,  6, 7, 2],
			"base:item/pride_flag":  ["base:ghost/normal",      "base:tileset/monomap", false, 32, 23, 8, 3],
			"base:item/nb_flag":     ["base:ghost/normal",      "base:tileset/monomap", false, 32, 26, 8, 3],
			"base:item/ace_flag":    ["base:ghost/normal",      "base:tileset/monomap", false, 32, 26, 7, 3]
		}]
	]
}
